verse/internal/storage_common/__init__.py
verse/internal/storage_common/_azure.py
verse/internal/storage_common/_google.py
verse/internal/storage_common/_redis.py
verse/internal/storage_common/py.typed
verse/internal/storage_core/__init__.py
verse/internal/storage_core/_attributes.py
verse/internal/storage_core/_comparator.py
verse/internal/storage_core/_component.py
verse/internal/storage_core/_index_helper.py
verse/internal/storage_core/_item_processor.py
verse/internal/storage_core/_models.py
verse/internal/storage_core/_operation.py
verse/internal/storage_core/_operation_parser.py
verse/internal/storage_core/_parameter_parser.py
verse/internal/storage_core/_provider.py
verse/internal/storage_core/_validator.py
verse/internal/storage_core/py.typed
verse/storage/config_store/__init__.py
verse/storage/config_store/_constants.py
verse/storage/config_store/_helper.py
verse/storage/config_store/_models.py
verse/storage/config_store/component.py
verse/storage/config_store/providers/aws_parameter_store.py
verse/storage/config_store/providers/azure_app_configuration.py
verse/storage/config_store/providers/default.py
verse/storage/config_store/providers/document_store_provider.py
verse/storage/config_store/providers/env.py
verse/storage/config_store/providers/env_file.py
verse/storage/config_store/providers/google_runtime_configurator.py
verse/storage/config_store/providers/hosted.py
verse/storage/config_store/providers/local.py
verse/storage/config_store/providers/yaml_file.py
verse/storage/config_store/py.typed
verse/storage/document_store/__init__.py
verse/storage/document_store/_feature.py
verse/storage/document_store/_helper.py
verse/storage/document_store/_models.py
verse/storage/document_store/component.py
verse/storage/document_store/providers/amazon_dynamodb.py
verse/storage/document_store/providers/azure_cosmos_db.py
verse/storage/document_store/providers/default.py
verse/storage/document_store/providers/google_firestore.py
verse_storage-0.0.32.dist-info/LICENSE
verse_storage-0.0.32.dist-info/METADATA
verse_storage-0.0.32.dist-info/WHEEL
verse_storage-0.0.32.dist-info/RECORD
